{
  "action_space": [
    {
      "steering_angle": 60,
      "speed": 0.05,
      "index": 0
    },
    {
      "steering_angle": 30,
      "speed": 0.05,
      "index": 1
    },
    {
      "steering_angle": 0,
      "speed": 0.05,
      "index": 2
    },
    {
      "steering_angle": -30,
      "speed": 0.05,
      "index": 3
    },
    {
      "steering_angle": -60,
      "speed": 0.05,
      "index": 4
    },
    {
      "steering_angle": 60,
      "speed": 0,
      "index": 5
    },
    {
      "steering_angle": 30,
      "speed": 0,
      "index": 6
    },
    {
      "steering_angle": 0,
      "speed": 0,
      "index": 7
    },
    {
      "steering_angle": -30,
      "speed": 0,
      "index": 8
    },
    {
      "steering_angle": -60,
      "speed": 0,
      "index": 9
    }
  ]
}
